__init__.py
cli.py
extractor.py
qrreader.py
protobuff/gauth_pb2.py
gauth_extractor-0.0.8.dist-info/LICENSE
gauth_extractor-0.0.8.dist-info/METADATA
gauth_extractor-0.0.8.dist-info/WHEEL
gauth_extractor-0.0.8.dist-info/entry_points.txt
gauth_extractor-0.0.8.dist-info/top_level.txt
gauth_extractor-0.0.8.dist-info/RECORD
